{
    "defaultSeverity": "error",
    "extends": [
        "tslint-config-airbnb",
        "tslint-config-prettier"
    ],
    "jsRules": {},
    "rules": {
        "interface-name": [ "never-prefix" ],
        "member-access": [
            false
        ],
        "ordered-imports": [
            false
        ],
        "no-console": [
            false
        ],
        "no-var-requires": false,
        "variable-name": false,
        "function-name": false,
        "jsx-no-lambda": false
    },
    "rulesDirectory": []
}